[1,["bbB+EilqxEI7SVoWLZThsz@f9941","ddmRjmb2NDhbrkVxOKLwU3@f9941","ddyEwRBu9N34wz9ENvpDcS","bbB+EilqxEI7SVoWLZThsz@6c48a","cbZzoJZt5PZKJ7/xO2ejls@6c48a","ddmRjmb2NDhbrkVxOKLwU3@6c48a","cbZzoJZt5PZKJ7/xO2ejls@f9941"],["node","_spriteFrame","_textureSource","root","data","valueLabel","mysteryPrefab"],[["cc.Node",["_name","_layer","_components","_prefab","_parent","_lpos","_children"],1,9,4,1,5,2],"cc.SpriteFrame",["cc.UITransform",["node","__prefab","_contentSize","_anchorPoint"],3,1,4,5,5],["cc.Sprite",["_sizeMode","node","__prefab","_spriteFrame","_color"],2,1,4,6,5],["cc.Prefab",["_name"],2],["cc.Node",["_name","_layer","_parent","_components","_prefab","_lpos"],1,1,12,4,5],["cc.CompPrefabInfo",["fileId"],2],["fe478HbBWxHc6X8xFFVtLeh",["itemType","modifierType","node","__prefab","valueLabel","mysteryPrefab"],1,1,4,1,6],["cc.PrefabInfo",["fileId","instance","targetOverrides","nestedPrefabInstanceRoots","root","asset"],-1,1,1],["cc.Label",["_string","_actualFontSize","_fontSize","_lineHeight","_isBold","_enableOutline","node","__prefab","_color","_outlineColor"],-3,1,4,5,5]],[[6,0,2],[8,0,1,2,3,4,5,5],[2,0,1,2,1],[3,0,1,2,4,3,2],[4,0,2],[0,0,1,6,2,3,3],[0,0,1,4,6,2,3,5,3],[0,0,1,4,2,3,3],[0,0,1,4,2,3,5,3],[0,0,1,2,3,5,3],[5,0,1,2,3,4,5,3],[2,0,1,1],[2,0,1,2,3,1],[7,0,1,2,3,4,5,3],[3,1,2,3,1],[9,0,1,2,3,4,5,6,7,8,9,7]],[[[[4,"StickyMultiplier"],[5,"StickyMultiplier",33554432,[-5,-6,-7],[[11,-2,[0,"6ajoTXsg1Jhbw/sGmNQo5X"]],[13,"modifier","stickyMultiplier",-4,[0,"93c3L2RZFFqJotoKBurjBN"],-3,3]],[1,"3eT1e6yRpDrLR7EzNDLHoO",null,null,null,-1,0]],[6,"repeat-icon",33554432,1,[-10],[[2,-8,[0,"a6QihiSgFK24GFK4B4icVM"],[5,40,40]],[3,0,-9,[0,"5bnLkbqaZBtKkrSM6rcNWx"],[4,4278190080],2]],[1,"69lNSprV9PYaH1vjIC6W7s",null,null,null,1,0],[1,0,-65,0]],[7,"Coin",33554432,1,[[2,-11,[0,"4eaG05bQtHwKlVhj5xJwQS"],[5,145,145]],[3,0,-12,[0,"93NOsDflNCcbDvXwXcnFZZ"],[4,4292804503],0]],[1,"22XtFSkoFLRKTqvDQEB5HF",null,null,null,1,0]],[10,"Value",33554432,1,[[[2,-13,[0,"65QyuhnatK17rXoICASJAo"],[5,73.50123789878822,105.69999999999999]],-14],4,1],[1,"21W9wcrExA66RKdaLkbuEN",null,null,null,1,0],[1,0,8,0]],[8,"repeat-icon-001",33554432,2,[[2,-15,[0,"7eO/Hw9QdM/oUmBKK2uGd4"],[5,40,40]],[3,0,-16,[0,"e5IwSbQYVKups1RAtZ868C"],[4,4284602879],1]],[1,"65pHBBA65Eq7bL5Ohoob4J",null,null,null,1,0],[1,-1,2,0]],[15,"x\n2.0",59.81481481481481,50,45,true,true,4,[0,"61tncdQPJM+70irYOtThJ5"],[4,4284602879],[4,4280221696]]],0,[0,3,1,0,0,1,0,5,6,0,0,1,0,-1,3,0,-2,4,0,-3,2,0,0,2,0,0,2,0,-1,5,0,0,3,0,0,3,0,0,4,0,-2,6,0,0,5,0,0,5,0,4,1,16],[0,0,0,0],[1,1,1,6],[1,0,0,2]],[[{"name":"repeat-icon","rect":{"x":4,"y":10,"width":504,"height":492},"offset":{"x":0,"y":0},"originalSize":{"width":512,"height":512},"rotated":false,"capInsets":[0,0,0,0],"vertices":{"rawPosition":[-252,-246,0,252,-246,0,-252,246,0,252,246,0],"indexes":[0,1,2,2,1,3],"uv":[4,502,508,502,4,10,508,10],"nuv":[0.0078125,0.01953125,0.9921875,0.01953125,0.0078125,0.98046875,0.9921875,0.98046875],"minPos":{"x":-252,"y":-246,"z":0},"maxPos":{"x":252,"y":246,"z":0}},"packable":true,"pixelsToUnit":100,"pivot":{"x":0.5,"y":0.5},"meshType":0}],[1],0,[0],[2],[3]],[[{"name":"Door","rect":{"x":0,"y":0,"width":154,"height":154},"offset":{"x":0,"y":0},"originalSize":{"width":154,"height":154},"rotated":false,"capInsets":[0,0,0,0],"vertices":{"rawPosition":[-77,-77,0,77,-77,0,-77,77,0,77,77,0],"indexes":[0,1,2,2,1,3],"uv":[0,154,154,154,0,0,154,0],"nuv":[0,0,1,0,0,1,1,1],"minPos":{"x":-77,"y":-77,"z":0},"maxPos":{"x":77,"y":77,"z":0}},"packable":true,"pixelsToUnit":100,"pivot":{"x":0.5,"y":0.5},"meshType":0}],[1],0,[0],[2],[4]],[[{"name":"coinWhite","rect":{"x":14,"y":13,"width":228,"height":229},"offset":{"x":0,"y":0.5},"originalSize":{"width":256,"height":256},"rotated":false,"capInsets":[0,0,0,0],"vertices":{"rawPosition":[-114,-114.5,0,114,-114.5,0,-114,114.5,0,114,114.5,0],"indexes":[0,1,2,2,1,3],"uv":[14,243,242,243,14,14,242,14],"nuv":[0.0546875,0.0546875,0.9453125,0.0546875,0.0546875,0.94921875,0.9453125,0.94921875],"minPos":{"x":-114,"y":-114.5,"z":0},"maxPos":{"x":114,"y":114.5,"z":0}},"packable":true,"pixelsToUnit":100,"pivot":{"x":0.5,"y":0.5},"meshType":0}],[1],0,[0],[2],[5]],[[[4,"MysterySprite"],[9,"MysterySprite",33554432,[[12,-2,[0,"7037JXk7tEsYE8DyO4fRzv"],[5,154,154],[0,0.5,0]],[14,-3,[0,"11EaxZGClN+a2bKJaidPwB"],0]],[1,"6evM9z7uBKI5YvAuFSos5F",null,null,null,-1,0],[1,0,-77,0]]],0,[0,3,1,0,0,1,0,0,1,0,4,1,3],[0],[1],[6]]]]
